adapto/__init__.py
adapto/aws_lambda_monitor.py
adapto/aws_lambda_scaler.py
adapto/predictor.py
adapto/scaler.py
adapto/utils.py
adapto-0.1.5.dist-info/LICENSE
adapto-0.1.5.dist-info/METADATA
adapto-0.1.5.dist-info/WHEEL
adapto-0.1.5.dist-info/top_level.txt
adapto-0.1.5.dist-info/RECORD
