Metadata-Version: 2.2
Name: adapto
Version: 0.1.5
Summary: AI-driven auto-scaling library for dynamic resource allocation.
Home-page: https://github.com/hrshlmeht/adapto
Author: Harshal Mehta
Author-email: harshalmehta1998@gmail.com
Classifier: Programming Language :: Python :: 3
Classifier: License :: OSI Approved :: MIT License
Classifier: Operating System :: OS Independent
Requires-Python: >=3.7
License-File: LICENSE
Requires-Dist: psutil
Requires-Dist: numpy
Dynamic: author
Dynamic: author-email
Dynamic: classifier
Dynamic: home-page
Dynamic: requires-dist
Dynamic: requires-python
Dynamic: summary
